LICENSE
MANIFEST.in
README.md
setup.py
dnoticias_backoffice/__init__.py
dnoticias_backoffice/apps.py
dnoticias_backoffice/components.py
dnoticias_backoffice/context_processors.py
dnoticias_backoffice/forms.py
dnoticias_backoffice/menu.py
dnoticias_backoffice/serializers.py
dnoticias_backoffice/urls.py
dnoticias_backoffice/views.py
dnoticias_backoffice.egg-info/PKG-INFO
dnoticias_backoffice.egg-info/SOURCES.txt
dnoticias_backoffice.egg-info/dependency_links.txt
dnoticias_backoffice.egg-info/requires.txt
dnoticias_backoffice.egg-info/top_level.txt
dnoticias_backoffice/__pycache__/__init__.cpython-39.pyc
dnoticias_backoffice/__pycache__/forms.cpython-39.pyc
dnoticias_backoffice/__pycache__/serializers.cpython-39.pyc
dnoticias_backoffice/__pycache__/urls.cpython-39.pyc
dnoticias_backoffice/__pycache__/views.cpython-39.pyc
dnoticias_backoffice/templates/backoffice/groups/form.html
dnoticias_backoffice/templates/backoffice/masters/form.html
dnoticias_backoffice/templates/backoffice/masters/main.html
dnoticias_backoffice/templates/backoffice/masters/includes/footer.html
dnoticias_backoffice/templates/backoffice/masters/includes/header.html
dnoticias_backoffice/templates/backoffice/masters/includes/menu.html
dnoticias_backoffice/templates/backoffice/masters/includes/messages.html
dnoticias_backoffice/templates/backoffice/masters/includes/nav-bo.html
dnoticias_backoffice/templates/backoffice/masters/includes/notifications.html
dnoticias_backoffice/templates/backoffice/masters/includes/user.html
dnoticias_backoffice/templates/backoffice/permissions/form.html
dnoticias_backoffice/templates/components/README.md
dnoticias_backoffice/templates/components/menu_category.html
dnoticias_backoffice/templates/components/menu_item.html
dnoticias_backoffice/templates/components/forms/checkbox.html
dnoticias_backoffice/templates/components/forms/checklist.html
dnoticias_backoffice/templates/components/forms/datetime.html
dnoticias_backoffice/templates/components/forms/dual_listbox.html
dnoticias_backoffice/templates/components/forms/image.html
dnoticias_backoffice/templates/components/forms/input.html
dnoticias_backoffice/templates/components/forms/input_code.html
