Metadata-Version: 2.1
Name: dnoticias_backoffice
Version: 1.2.1
Home-page: https://www.dnoticias.pt/
Author: Pedro Mendes
Author-email: pedro.trabalho.uma@gmail.com
Maintainer: Nélson Gomes
Maintainer-email: ngoncalves@dnoticias.pt
License: MIT
License-File: LICENSE
Requires-Dist: django
Requires-Dist: django-flags
Requires-Dist: djangorestframework
Requires-Dist: django-dnoticias-tables
Requires-Dist: slippers
